pkg_wordslookup/__init__.py
pkg_wordslookup/pkg_wordslookup.py
pkg_wordslookup/zen.txt
pkg_wordslookup-1.0.1.dist-info/LICENSE
pkg_wordslookup-1.0.1.dist-info/WHEEL
pkg_wordslookup-1.0.1.dist-info/METADATA
pkg_wordslookup-1.0.1.dist-info/RECORD
