Metadata-Version: 2.1
Name: pkg-wordslookup
Version: 1.0.1
Summary: This package will look the instances of a specific word provided as an input inside a file also provided as an input. The package will give the amount of times the word is in the file and it will print the line in which the word is placed
License: MIT
Author: Gabriel Coronel
Requires-Python: >=3.9,<4.0
Classifier: License :: OSI Approved :: MIT License
Classifier: Programming Language :: Python :: 3
Classifier: Programming Language :: Python :: 3.9
Classifier: Programming Language :: Python :: 3.10
Classifier: Programming Language :: Python :: 3.11
